zoho_inventory_prefect_tasks/__init__.py
zoho_inventory_prefect_tasks/_version.py
zoho_inventory_prefect_tasks/tasks/__init__.py
zoho_inventory_prefect_tasks/tasks/contact_persons.py
zoho_inventory_prefect_tasks/tasks/contacts.py
zoho_inventory_prefect_tasks/tasks/items.py
zoho_inventory_prefect_tasks/tasks/sales_orders.py
zoho_inventory_prefect_tasks/tasks/shipment_orders.py
zoho_inventory_prefect_tasks-0.0.5.dist-info/LICENSE
zoho_inventory_prefect_tasks-0.0.5.dist-info/METADATA
zoho_inventory_prefect_tasks-0.0.5.dist-info/WHEEL
zoho_inventory_prefect_tasks-0.0.5.dist-info/top_level.txt
zoho_inventory_prefect_tasks-0.0.5.dist-info/RECORD
