Metadata-Version: 2.1
Name: zoho-inventory-prefect-tasks
Version: 0.0.5
Summary: UNKNOWN
Home-page: https://github.com/aporacloudmobile/zoho_inventory_prefect_tasks
Author: Carlos Paiva
Author-email: carlospaiva87@gmail.com
License: UNKNOWN
Platform: UNKNOWN
Classifier: Programming Language :: Python :: 3
Classifier: Operating System :: OS Independent
Requires-Python: >=3.6
License-File: LICENSE
Requires-Dist: requests (>=2.25.1)
Requires-Dist: jsonmerge (>=1.8.0)
Requires-Dist: versioneer (~=0.19)
Requires-Dist: setuptools (>=58.5.3)
Requires-Dist: pytest (>=6.1.0)
Requires-Dist: prefect (==0.15.11)
Requires-Dist: zoho-inventory-python-sdk (>=0.0.9)
Requires-Dist: boto3 (>=1.24.53)
Requires-Dist: botocore (>=1.27.53)
